LICENSE
MANIFEST.in
README.rst
pyproject.toml
setup.py
classylss/__init__.py
classylss/astropy_compat.py
classylss/binding.cpp
classylss/binding.pyx
classylss/cclassy.pxd
classylss/version.py
classylss.egg-info/PKG-INFO
classylss.egg-info/SOURCES.txt
classylss.egg-info/dependency_links.txt
classylss.egg-info/requires.txt
classylss.egg-info/top_level.txt
depends/Makefile
depends/copy_data_files
depends/install_class.sh