Metadata-Version: 2.4
Name: classylss
Version: 0.3.1
Summary: More Extensive Python binding of the CLASS CMB Boltzmann code
Home-page: http://github.com/nickhand/classylss
Author: Nick Hand, Yu Feng, Simeon Bird
Author-email: spb@ucr.edu
License: GPL3
License-File: LICENSE
Requires-Dist: numpy
Requires-Dist: Cython
Provides-Extra: tests
Requires-Dist: pytest; extra == "tests"
Requires-Dist: astropy; extra == "tests"
Requires-Dist: scipy; extra == "tests"
Dynamic: author
Dynamic: author-email
Dynamic: home-page
Dynamic: license
Dynamic: license-file
Dynamic: provides-extra
Dynamic: requires-dist
Dynamic: summary
